{
  "meta": {
    "pr": 28,
    "repo": "kunpengcompute/kupl",
    "pr_url": "https://gitcode.com/kunpengcompute/kupl/pull/28",
    "pipeline_name": "PR-pipeline_kupl#74",
    "pipeline_state": " [ commitID：15762ca0 ] 已完成",
    "pipeline_url": "https://www.openlibing.com/apps/pipelineDetail?projectId=300073&pipelineId=ce7db2cf206c4fc9a9e9431508388296&pipelineRunId=8921703ae0254317bcb9bdaf8a123ee5&codeHostingPlatformFlag=gitcode",
    "comment_time": "",
    "fetched_at": "2026-06-18T10:49:52.383516+08:00",
    "analyzed_at": "2026-06-18T10:55:00.000000+08:00",
    "analysis_method": "ai_semantic"
  },
  "builds": [
    {
      "task_name": "Build_gcc",
      "stage": "编译构建",
      "status": "passed",
      "detail_url": "https://www.openlibing.com/apps/pipelineDetail?projectId=300073&pipelineId=ce7db2cf206c4fc9a9e9431508388296&pipelineRunId=8921703ae0254317bcb9bdaf8a123ee5&stepId=8e3c6d4b2b86410b9c5783c20bdc32e3&jobRunId=d87d9824743443bdaf42debdb7ca7710&stepRunId=515b8090a6f241c8a8aa85c149091365&codeHostingPlatformFlag=gitcode",
      "time": {
        "start": "2026-06-08T11:07:31.813000+08:00",
        "end": "2026-06-08T11:07:46.055000+08:00",
        "duration_seconds": 14.242
      },
      "pre_build": {
        "total_seconds": 5.387,
        "pct_of_total": 37.8,
        "orchestrator": "docker",
        "actions": [
          {
            "key": "node_assignment",
            "name": "执行节点分配",
            "start": "2026-06-08T11:07:31.918+08:00",
            "end": "2026-06-08T11:07:32.087+08:00",
            "duration_seconds": 0.169,
            "evidence": "[PRE_ENV:slave_create] 开始 11:07:31.918 → Find available executor node:agent_CI_MR_02-VnIJl3dkf4 11:07:32.030 → 执行完成 11:07:32.087"
          },
          {
            "key": "docker_pull",
            "name": "Docker 镜像拉取",
            "start": "2026-06-08T11:07:32.446+08:00",
            "end": "2026-06-08T11:07:36.072+08:00",
            "duration_seconds": 3.626,
            "evidence": "arm-shell4.2.46-git2.23-zip-1.1.0 (CI runner): Image is up to date 11:07:32.446; v1.0 cloud-hpckit/hpckit_openeuler_22.03_lts_sp2_arm (build container): Image is up to date 11:07:36.072. Both images cached, no actual pull time; gap is CI overhead between git_checkout and container launch."
          },
          {
            "key": "git_checkout",
            "name": "代码检出(CI机)",
            "start": "2026-06-08T11:07:33.263+08:00",
            "end": "2026-06-08T11:07:34.401+08:00",
            "duration_seconds": 1.138,
            "evidence": "[代码检出:external_pre_checkout] 开始 11:07:33.263 → git clone kunpengcompute/kupl.git → fork MR merge 15762ca0 → [代码检出:external_post_checkout] 完成 11:07:34.401"
          },
          {
            "key": "env_setup",
            "name": "环境变量+容器初始化",
            "start": "2026-06-08T11:07:36.072+08:00",
            "end": "2026-06-08T11:07:37.200+08:00",
            "duration_seconds": 1.128,
            "evidence": "swr build image pull check 11:07:36.072 → container start → set -ex, export PATH=/opt/buildtools/gcc-12.3.1-2025.06-aarch64-linux/bin:..., export INCLUDE=..., export LD_LIBRARY_PATH=... → sh build.sh --compiler=gcc --enable_mma=on 11:07:37.200"
          }
        ]
      },
      "build_phases": {
        "total_seconds": 3.645,
        "pct_of_total": 25.6,
        "actions": [
          {
            "key": "cmake_configure",
            "name": "CMake 配置",
            "duration_seconds": 0.655
          },
          {
            "key": "compilation",
            "name": "编译 (make/gcc)",
            "duration_seconds": 2.990
          }
        ]
      },
      "summary": {
        "pre_build_seconds": 5.387,
        "build_seconds": 3.645,
        "unattributed_seconds": 5.21,
        "key_bottleneck": "git_checkout",
        "key_bottleneck_seconds": 1.138
      }
    },
    {
      "task_name": "Build_bisheng",
      "stage": "编译构建",
      "status": "passed",
      "detail_url": "https://www.openlibing.com/apps/pipelineDetail?projectId=300073&pipelineId=ce7db2cf206c4fc9a9e9431508388296&pipelineRunId=8921703ae0254317bcb9bdaf8a123ee5&stepId=8e3c6d4b2b86410b9c5783c20bdc32e3&jobRunId=d6134737d5b5439298ccb2692c723b2c&stepRunId=f05cd7807fb7489eb63c6e147acc5bdd&codeHostingPlatformFlag=gitcode",
      "time": {
        "start": "2026-06-08T11:07:31.983000+08:00",
        "end": "2026-06-08T11:08:12.732000+08:00",
        "duration_seconds": 40.749
      },
      "pre_build": {
        "total_seconds": 27.341,
        "pct_of_total": 67.1,
        "orchestrator": "docker",
        "actions": [
          {
            "key": "node_assignment",
            "name": "执行节点分配",
            "start": "2026-06-08T11:07:32.093+08:00",
            "end": "2026-06-08T11:07:54.373+08:00",
            "duration_seconds": 22.28,
            "evidence": "[PRE_ENV:slave_create] 开始 11:07:32.093 → Start to create an executor node... 11:07:33.097 → [21.23s wait for available node] → Find available executor node:agent_CI_MR_02-VnIJl3dkf4 11:07:54.327 → 执行完成 11:07:54.373"
          },
          {
            "key": "docker_pull",
            "name": "Docker 镜像拉取",
            "start": "2026-06-08T11:07:54.731+08:00",
            "end": "2026-06-08T11:07:58.189+08:00",
            "duration_seconds": 3.458,
            "evidence": "arm-shell4.2.46-git2.23-zip-1.1.0 (CI runner): Image is up to date 11:07:54.731; v1.0 cloud-hpckit/hpckit_openeuler_22.03_lts_sp2_arm (build container): Image is up to date 11:07:58.189. Both images cached, no actual pull time; gap includes CI overhead and git checkout (interleaved timestamps)."
          },
          {
            "key": "git_checkout",
            "name": "代码检出(CI机)",
            "start": "2026-06-08T11:07:55.586+08:00",
            "end": "2026-06-08T11:07:56.521+08:00",
            "duration_seconds": 0.935,
            "evidence": "[代码检出:external_pre_checkout] 开始 11:07:55.586 → git clone kunpengcompute/kupl.git → fork MR merge 15762ca0 → [代码检出:external_post_checkout] 完成 11:07:56.521"
          },
          {
            "key": "env_setup",
            "name": "环境变量+容器初始化",
            "start": "2026-06-08T11:07:58.189+08:00",
            "end": "2026-06-08T11:07:59.324+08:00",
            "duration_seconds": 1.135,
            "evidence": "swr build image pull check 11:07:58.189 → container start → set -ex, BISHENG_PATH=/opt/buildtools/BiShengCompiler-..., export PATH=.../BiShengCompiler-.../bin:..., export LD_LIBRARY_PATH=... → sh build.sh --compiler=clang --enable_mma=on 11:07:59.324"
          }
        ]
      },
      "build_phases": {
        "total_seconds": 4.534,
        "pct_of_total": 11.1,
        "actions": [
          {
            "key": "cmake_configure",
            "name": "CMake 配置",
            "duration_seconds": 0.831
          },
          {
            "key": "compilation",
            "name": "编译 (make/clang)",
            "duration_seconds": 3.431
          },
          {
            "key": "packaging",
            "name": "安装",
            "duration_seconds": 0.272
          }
        ]
      },
      "summary": {
        "pre_build_seconds": 27.341,
        "build_seconds": 4.534,
        "unattributed_seconds": 8.874,
        "key_bottleneck": "node_assignment",
        "key_bottleneck_seconds": 22.28
      }
    }
  ]
}
